{"best_config": {"model": "featNTL", "network": "featNTL", "trainer": "NTL", "device": "cuda", "batch_size": 512, "learning_rate": 0.0004, "training_epochs": 30, "train_method": "refine", "enc_zdim": 256, "enc_nlayers": 2, "num_trans": 15, "trans_nlayers": 3, "trans_hdim": 2048, "trans_type": "forward", "loss": "DCL", "batch_norm": false, "loss_temp": 0.1, "l2": 0.0, "optimizer": "Adam", "scheduler": {"class": "StepLR", "args": {"step_size": 30, "gamma": 0.5}}, "early_stopper": {"class": "Patience", "args": {"patience": 10, "use_train_loss": true}}, "shuffle": true, "num_repeat": 5, "save_scores": false, "result_folder": "RESULTS/", "dataset": "fmnist"}, "VAL_AUC": [0.8551277777777778, 0.8639305555555555, 0.8610061666666667, 0.8597151666666668, 0.8559912222222222], "TS_F1": [0.9369409411633979, 0.9399411078393243, 0.9370520584476916, 0.9365555555555556, 0.9366596288476498], "TS_AP": [0.9787057532059565, 0.9799349426430896, 0.979494228147656, 0.9793105798458668, 0.9789709568168635], "TS_AUC": [0.8551277777777778, 0.8639305555555555, 0.8610061666666667, 0.8597151666666668, 0.8559912222222222]}