{"best_config": {"model": "featNTL", "network": "featNTL", "trainer": "NTL", "device": "cuda", "batch_size": 512, "learning_rate": 0.0004, "training_epochs": 30, "train_method": "loe_soft", "enc_zdim": 256, "enc_nlayers": 2, "num_trans": 15, "trans_nlayers": 3, "trans_hdim": 2048, "trans_type": "forward", "loss": "DCL", "batch_norm": false, "loss_temp": 0.1, "l2": 0.0, "optimizer": "Adam", "scheduler": {"class": "StepLR", "args": {"step_size": 30, "gamma": 0.5}}, "early_stopper": {"class": "Patience", "args": {"patience": 10, "use_train_loss": true}}, "shuffle": true, "num_repeat": 5, "save_scores": false, "result_folder": "RESULTS/", "dataset": "fmnist"}, "VAL_AUC": [0.9235669444444444, 0.9179590000000001, 0.9210665, 0.9198264444444444, 0.9260933333333333], "TS_F1": [0.9541641202289016, 0.9518306572587365, 0.9538888888888889, 0.9542752375131952, 0.9551641757875438], "TS_AP": [0.9905142340258942, 0.9896196788360684, 0.9901478693439885, 0.9899584934715732, 0.9908186675259584], "TS_AUC": [0.9235669444444444, 0.9179590000000001, 0.9210665, 0.9198264444444444, 0.9260933333333333]}