{"best_config": {"model": "featNTL", "network": "featNTL", "trainer": "NTL", "device": "cuda", "batch_size": 512, "learning_rate": 0.0004, "training_epochs": 30, "train_method": "loe_hard", "enc_zdim": 256, "enc_nlayers": 2, "num_trans": 15, "trans_nlayers": 3, "trans_hdim": 2048, "trans_type": "forward", "loss": "DCL", "batch_norm": false, "loss_temp": 0.1, "l2": 0.0, "optimizer": "Adam", "scheduler": {"class": "StepLR", "args": {"step_size": 30, "gamma": 0.5}}, "early_stopper": {"class": "Patience", "args": {"patience": 10, "use_train_loss": true}}, "shuffle": true, "num_repeat": 5, "save_scores": false, "result_folder": "RESULTS/", "dataset": "fmnist"}, "VAL_AUC": [0.7281017222222222, 0.7280526111111111, 0.7590083888888888, 0.6756268333333333, 0.6988740555555556], "TS_F1": [0.9120506694816378, 0.9127173731873993, 0.9159397744319129, 0.9042724595810878, 0.9056561840204468], "TS_AP": [0.962808547670097, 0.9637695543045826, 0.9676589868306104, 0.9563954017148374, 0.9595837770251128], "TS_AUC": [0.7281017222222222, 0.7280526111111111, 0.7590083888888888, 0.6756268333333333, 0.6988740555555556]}