{"best_config": {"model": "featNTL", "network": "featNTL", "trainer": "NTL", "device": "cuda", "batch_size": 512, "learning_rate": 0.0004, "training_epochs": 30, "train_method": "refine", "enc_zdim": 256, "enc_nlayers": 2, "num_trans": 15, "trans_nlayers": 3, "trans_hdim": 2048, "trans_type": "forward", "loss": "DCL", "batch_norm": false, "loss_temp": 0.1, "l2": 0.0, "optimizer": "Adam", "scheduler": {"class": "StepLR", "args": {"step_size": 30, "gamma": 0.5}}, "early_stopper": {"class": "Patience", "args": {"patience": 10, "use_train_loss": true}}, "shuffle": true, "num_repeat": 5, "save_scores": false, "result_folder": "RESULTS/", "dataset": "fmnist"}, "VAL_AUC": [0.8765179999999999, 0.40689511111111115, 0.3884905, 0.373956, 0.5568166666666666], "TS_F1": [0.9382222222222222, 0.9045555555555556, 0.9128284904716929, 0.905, 0.9222222222222223], "TS_AP": [0.9833666788674829, 0.8489966285500689, 0.842219742926265, 0.8344702687103965, 0.8823190822439333], "TS_AUC": [0.8765179999999999, 0.40689511111111115, 0.3884905, 0.373956, 0.5568166666666666]}