{"best_config": {"model": "featNTL", "network": "featNTL", "trainer": "NTL", "device": "cuda", "batch_size": 512, "learning_rate": 0.0004, "training_epochs": 30, "train_method": "refine", "enc_zdim": 256, "enc_nlayers": 2, "num_trans": 15, "trans_nlayers": 3, "trans_hdim": 2048, "trans_type": "forward", "loss": "DCL", "batch_norm": false, "loss_temp": 0.1, "l2": 0.0, "optimizer": "Adam", "scheduler": {"class": "StepLR", "args": {"step_size": 30, "gamma": 0.5}}, "early_stopper": {"class": "Patience", "args": {"patience": 10, "use_train_loss": true}}, "shuffle": true, "num_repeat": 5, "save_scores": false, "result_folder": "RESULTS/", "dataset": "fmnist"}, "VAL_AUC": [0.9083272222222223, 0.9083576111111111, 0.9078014999999999, 0.9083741666666667, 0.9102501666666666], "TS_F1": [0.9437777777777778, 0.943163509083838, 0.9418301016723152, 0.944104900544505, 0.9434444444444444], "TS_AP": [0.9885220367436826, 0.9882455297119992, 0.9884418386903736, 0.9883818690324434, 0.9888427805127634], "TS_AUC": [0.9083272222222223, 0.9083576111111111, 0.9078014999999999, 0.9083741666666667, 0.9102501666666666]}