{"best_config": {"model": "featNTL", "network": "featNTL", "trainer": "NTL", "device": "cuda", "batch_size": 512, "learning_rate": 0.0004, "training_epochs": 30, "train_method": "simple_refine", "enc_zdim": 256, "enc_nlayers": 2, "num_trans": 15, "trans_nlayers": 3, "trans_hdim": 2048, "trans_type": "forward", "loss": "DCL", "batch_norm": false, "loss_temp": 0.1, "l2": 0.0, "optimizer": "Adam", "scheduler": {"class": "StepLR", "args": {"step_size": 30, "gamma": 0.5}}, "early_stopper": {"class": "Patience", "args": {"patience": 10, "use_train_loss": true}}, "shuffle": true, "num_repeat": 5, "save_scores": false, "result_folder": "RESULTS/", "dataset": "fmnist"}, "VAL_AUC": [0.8066589444444444, 0.7998459444444445, 0.8039891111111113, 0.7971904444444444, 0.7944442777777778], "TS_F1": [0.9274959719984444, 0.9274444444444444, 0.9277182065670314, 0.9262222222222222, 0.9267181510083894], "TS_AP": [0.9715362855614271, 0.9706642185612453, 0.9718373929718394, 0.9696628529458136, 0.9694654272647018], "TS_AUC": [0.8066589444444444, 0.7998459444444445, 0.8039891111111113, 0.7971904444444444, 0.7944442777777778]}