{"best_config": {"model": "featNTL", "network": "featNTL", "trainer": "NTL", "device": "cuda", "batch_size": 512, "learning_rate": 0.0004, "training_epochs": 30, "train_method": "refine", "enc_zdim": 256, "enc_nlayers": 2, "num_trans": 15, "trans_nlayers": 3, "trans_hdim": 2048, "trans_type": "forward", "loss": "DCL", "batch_norm": false, "loss_temp": 0.1, "l2": 0.0, "optimizer": "Adam", "scheduler": {"class": "StepLR", "args": {"step_size": 30, "gamma": 0.5}}, "early_stopper": {"class": "Patience", "args": {"patience": 10, "use_train_loss": true}}, "shuffle": true, "num_repeat": 5, "save_scores": false, "result_folder": "RESULTS/", "dataset": "fmnist"}, "VAL_AUC": [0.9450407777777778, 0.9466145555555554, 0.9276535555555556, 0.9302211666666667, 0.9374123888888889], "TS_F1": [0.9511111111111111, 0.9531640646702594, 0.9448888888888889, 0.9457192066225901, 0.9478888888888889], "TS_AP": [0.9938572207540561, 0.9940273766697034, 0.9918886816638046, 0.9921874426352185, 0.9930133197150607], "TS_AUC": [0.9450407777777778, 0.9466145555555554, 0.9276535555555556, 0.9302211666666667, 0.9374123888888889]}