{"best_config": {"model": "featNTL", "network": "featNTL", "trainer": "NTL", "device": "cuda", "batch_size": 512, "learning_rate": 0.0004, "training_epochs": 30, "train_method": "simple_refine", "enc_zdim": 256, "enc_nlayers": 2, "num_trans": 15, "trans_nlayers": 3, "trans_hdim": 2048, "trans_type": "forward", "loss": "DCL", "batch_norm": false, "loss_temp": 0.1, "l2": 0.0, "optimizer": "Adam", "scheduler": {"class": "StepLR", "args": {"step_size": 30, "gamma": 0.5}}, "early_stopper": {"class": "Patience", "args": {"patience": 10, "use_train_loss": true}}, "shuffle": true, "num_repeat": 5, "save_scores": false, "result_folder": "RESULTS/", "dataset": "fmnist"}, "VAL_AUC": [0.8127807222222222, 0.7931697777777779, 0.8070149444444444, 0.7547804444444444, 0.7831856666666668], "TS_F1": [0.9369409411633979, 0.9325555555555556, 0.9328888888888889, 0.9247180398911051, 0.9320517806544809], "TS_AP": [0.9701373374447639, 0.9684575423298769, 0.9699657852439288, 0.9611423580323617, 0.9653382379989126], "TS_AUC": [0.8127807222222222, 0.7931697777777779, 0.8070149444444444, 0.7547804444444444, 0.7831856666666668]}